<annotation>
	<folder>my-project-name</folder>
	<filename>sp01_img06.jpg</filename>
	<path>/my-project-name/sp01_img06.jpg</path>
	<source>
		<database>Unspecified</database>
	</source>
	<size>
		<width>2905</width>
		<height>2886</height>
		<depth>3</depth>
	</size>
	<object>
		<name>sp01</name>
		<pose>Unspecified</pose>
		<truncated>0</truncated>
		<difficult>0</difficult>
		<bndbox>
			<xmin>881</xmin>
			<ymin>538</ymin>
			<xmax>1028</xmax>
			<ymax>705</ymax>
		</bndbox>
	</object>
	<object>
		<name>sp01</name>
		<pose>Unspecified</pose>
		<truncated>0</truncated>
		<difficult>0</difficult>
		<bndbox>
			<xmin>1230</xmin>
			<ymin>730</ymin>
			<xmax>1370</xmax>
			<ymax>863</ymax>
		</bndbox>
	</object>
	<object>
		<name>sp01</name>
		<pose>Unspecified</pose>
		<truncated>0</truncated>
		<difficult>0</difficult>
		<bndbox>
			<xmin>729</xmin>
			<ymin>947</ymin>
			<xmax>876</xmax>
			<ymax>1087</ymax>
		</bndbox>
	</object>
	<object>
		<name>sp01</name>
		<pose>Unspecified</pose>
		<truncated>0</truncated>
		<difficult>0</difficult>
		<bndbox>
			<xmin>1052</xmin>
			<ymin>1039</ymin>
			<xmax>1173</xmax>
			<ymax>1166</ymax>
		</bndbox>
	</object>
	<object>
		<name>sp01</name>
		<pose>Unspecified</pose>
		<truncated>0</truncated>
		<difficult>0</difficult>
		<bndbox>
			<xmin>888</xmin>
			<ymin>1309</ymin>
			<xmax>1001</xmax>
			<ymax>1417</ymax>
		</bndbox>
	</object>
	<object>
		<name>sp01</name>
		<pose>Unspecified</pose>
		<truncated>0</truncated>
		<difficult>0</difficult>
		<bndbox>
			<xmin>395</xmin>
			<ymin>1720</ymin>
			<xmax>464</xmax>
			<ymax>1788</ymax>
		</bndbox>
	</object>
	<object>
		<name>sp01</name>
		<pose>Unspecified</pose>
		<truncated>0</truncated>
		<difficult>0</difficult>
		<bndbox>
			<xmin>431</xmin>
			<ymin>1765</ymin>
			<xmax>500</xmax>
			<ymax>1841</ymax>
		</bndbox>
	</object>
	<object>
		<name>sp01</name>
		<pose>Unspecified</pose>
		<truncated>0</truncated>
		<difficult>0</difficult>
		<bndbox>
			<xmin>1184</xmin>
			<ymin>2192</ymin>
			<xmax>1305</xmax>
			<ymax>2346</ymax>
		</bndbox>
	</object>
	<object>
		<name>sp01</name>
		<pose>Unspecified</pose>
		<truncated>0</truncated>
		<difficult>0</difficult>
		<bndbox>
			<xmin>1487</xmin>
			<ymin>1823</ymin>
			<xmax>1601</xmax>
			<ymax>1950</ymax>
		</bndbox>
	</object>
	<object>
		<name>sp01</name>
		<pose>Unspecified</pose>
		<truncated>0</truncated>
		<difficult>0</difficult>
		<bndbox>
			<xmin>1685</xmin>
			<ymin>1777</ymin>
			<xmax>1799</xmax>
			<ymax>1904</ymax>
		</bndbox>
	</object>
</annotation>